{
  "date": "2026-02-03",
  "title": "📢 January Updates — 2026",
  "tags": ["Features", "Improvements", "Bug Fixes"],
  "image": "https://sitepins.com/images/blog/product-updates/what-new-sitepins-2026.png",
  "details": "We kicked off 2026 with some major updates!\n\nHere's everything we shipped in January 2026:\n\n- **100+ Pre-configured Templates** — One-click setup with Astro, Hugo, and Next.js templates\n- **UI/UX Revamp** — A more polished, consistent, and user-friendly experience\n- **Multiple Branching Support** — Manage branches, create PRs, and merge directly from Sitepins\n- **Email-based Access** — Grant access to teammates and clients without requiring Git accounts\n- **Vercel Deployment** — Deploy and auto-sync changes from Sitepins\n- **GitLab Integration** — Now supporting GitLab alongside GitHub\n- **SEO Suggestion Improvements** — More accurate SEO suggestions and SERP preview\n- **Global Search** — Find files easily with Cmd/Ctrl + K\n- **Media File Rename** — Rename files directly in the CMS\n- **Bug Fixes** — Various bug fixes and performance improvements\n\nWe're committed to continuously making Sitepins better. If you're already using Sitepins, we'd love your feedback.\n\n> **Note:** Some features are only available for Pro users.\n\n[Read the full post →](https://sitepins.com/blog/whats-new-in-sitepins-january-2026)"
}
